{
    "ak47": [
        "Distinctive curved magazine fitted underneath",
        "Wooden or synthetic stock and foregrip",
        "Selector switch on the side of the receiver",
        "Metal body with pronounced gas tube above the barrel",
        "Long-barreled firearm"
    ],
    "american-flag": [
        "typically shows symbols related to the United States (e.g., U.S. flags in other contexts such as uniforms, patches, etc.)",
        "a blue rectangle (canton) in the upper left corner",
        "the presence of red, white, and blue colors",
        "a rectangular shape",
        "13 horizontal stripes alternating red and white"
    ],
    "backpack": [
        "a bag designed to be carried on the back",
        "multiple compartments or pockets",
        "often made of fabric, leather, or synthetic materials",
        "a top handle for carrying by hand",
        "may have additional features like buckles, drawstrings, or side mesh pockets"
    ],
    "baseball-bat": [
        "tapered at one end",
        "often has a handle at the thinner end",
        "smooth surface",
        "may have markings or branding near the handle",
        "typically made of wood or metal"
    ],
    "baseball-glove": [
        "usually tan, brown, or black in color",
        "glove made of leather",
        "a webbing between the thumb and index finger",
        "a closed back or sometimes open with a strap",
        "large, padded surface"
    ],
    "basketball-hoop": [
        "often found in a gymnasium, playground, or sports court setting",
        "mounted on a pole or attached to a wall",
        "height from the ground (usually 10 feet for standard hoops)",
        "rectangular or square shape of the backboard (usually transparent or solid)",
        "net hanging from the rim"
    ],
    "bat": [
        "hanging upside down (occasionally)",
        "pointed ears",
        "dark fur or hairless skin",
        "sharp teeth or fangs",
        "small eyes"
    ],
    "bathtub": [
        "drain at one end",
        "faucets and handles",
        "flat, even bottom for standing or sitting",
        "smooth, curved edges",
        "potentially surrounded by tiles or a shower curtain"
    ],
    "bear": [
        "thick fur, typically brown, black, or white (depending on species)",
        "powerful limbs",
        "noticeable hump on the shoulders (especially in grizzly bears)",
        "short tail",
        "rounded ears"
    ],
    "beer-mug": [
        "may contain a foamy beverage (beer)",
        "often marked with measurement lines or logos",
        "transparent (if glass) or opaque (if ceramic)",
        "sometimes has a thick bottom for stability",
        "wide mouth for easy drinking"
    ],
    "billiards": [
        "possible chalk cubes for cues",
        "a set of colored balls, often divided between solid and striped, with a single white cue ball",
        "a triangle rack used to arrange the balls at the start of play",
        "a raised edge (cushion) surrounding the play area on the table",
        "six pockets along the sides and corners of the table"
    ],
    "binoculars": [
        "two smaller eyepieces at the back",
        "strap or harness attached",
        "optical device with two parallel telescopes",
        "black or dark-colored housing, though can come in various colors",
        "often a bridge connecting the two tubes"
    ],
    "birdbath": [
        "Shallow basin or bowl",
        "Sometimes includes decorative elements such as carvings, statues, or fountains",
        "Water present in the basin for birds to drink or bathe in",
        "Typically found in outdoor settings like gardens and yards",
        "Often made of stone, concrete, ceramic, or metal"
    ],
    "blimp": [
        "usually seen floating in the sky",
        "fins or rudders at the tail end for stability and steering",
        "often featuring advertising or branding along the sides",
        "propellers or engines mounted on the sides or at the rear",
        "large, elongated, and cylindrical shape"
    ],
    "bonsai-101": [
        "miniature tree",
        "small pot or container",
        "intricate branches",
        "meticulously pruned shape",
        "sometimes features rocks or decorative elements in the pot"
    ],
    "boom-box": [
        "an antenna for radio reception",
        "cassette tape deck(s)",
        "large speakers on the front",
        "rectangular or box-like shape",
        "knobs or dials for volume and tuning"
    ],
    "bowling-ball": [
        "typically made of a hard material like plastic or urethane",
        "often has manufacturer logos or brand markings",
        "standard size relative to human hand",
        "multiple finger holes (usually three) for gripping",
        "smooth, glossy surface"
    ],
    "bowling-pin": [
        "used in bowling alleys on a polished wooden lane",
        "wider base compared to the neck",
        "typically made of wood or plastic",
        "approximately 15 inches tall",
        "often seen in groups of ten arranged in a triangular pattern"
    ],
    "boxing-glove": [
        "slightly bulbous, oversized appearance compared to a bare hand",
        "a Velcro strap or laces around the wrist",
        "a distinct separation for the thumb",
        "typically bright, solid colors (red, blue, black, etc.)",
        "often made of leather or synthetic materials"
    ],
    "brain-101": [],
    "breadmaker": [
        "Built-in loaf pan (often visible inside if the lid is open)",
        "Kneading paddle inside the loaf pan (visible if the pan is open)",
        "Rectangular or box-like shape",
        "Control panel with buttons or digital display",
        "Ventilation slots or small steam vents on the top or sides"
    ],
    "buddha-101": [],
    "bulldozer": [
        "large tracks or wheels for movement",
        "sometimes seen with attachments like rippers at the back",
        "wide metal blade at the front",
        "exhaust pipe and engine housing",
        "often yellow or orange"
    ],
    "butterfly": [
        "Compound eyes",
        "Patterns or markings on the wings",
        "Six legs",
        "Two pairs of large, colorful wings",
        "Proboscis (a long, coiled feeding tube)"
    ],
    "cactus": [
        "Ribbed or columnar shape",
        "Thick, fleshy stems",
        "Flowering during certain seasons",
        "Spines or thorns",
        "Absence of traditional leaves (or reduced to spines)"
    ],
    "cake": [
        "cake stand, plate, or serving tray",
        "baked dessert",
        "various colors and textures",
        "typically round or rectangular in shape",
        "icing or frosting on the surface"
    ],
    "calculator": [
        "a display screen for showing numbers and operations",
        "rectangular or slightly curved shape",
        "additional function keys (e.g., %, \u00b1, clear, square root)",
        "a numerical keypad (0-9)",
        "sometimes a battery compartment at the back or bottom"
    ],
    "camel": [
        "Coarse, sandy-colored fur",
        "Shaggy winter coat (sometimes visible)",
        "Big, expressive eyes with long eyelashes",
        "Large, humped mammal",
        "Large, padded feet with two toes"
    ],
    "cannon": [
        "historical or antique look, often associated with military or naval scenes",
        "thick walls on the barrel indicating strength",
        "large, cylindrical barrel",
        "sometimes accompanied by cannonballs",
        "typically made of metal (often black or dark gray)"
    ],
    "canoe": [
        "elongated, narrow shape",
        "paddles (single-bladed) often visible either inside or alongside",
        "sometimes features floatation devices or tethers",
        "wooden, aluminum, fiberglass, or plastic material",
        "usually found in a body of water (lake, river, etc.)"
    ],
    "car-tire": [
        "Metallic wheel rim in the center (when mounted)",
        "Rubber material",
        "Black or dark color",
        "Tread patterns on the outer surface",
        "Circular and ring-shaped"
    ],
    "cartman": [],
    "cd": [
        "Reflective, metallic surface on one side",
        "Thin and lightweight",
        "Circular, disc-shaped object",
        "Often comes in a plastic or paper case",
        "Often a small central hole"
    ],
    "centipede": [
        "antennae extending from the head",
        "color varies but often shades of brown, red, or yellow",
        "a smaller pair of compound eyes or simple eyes on the head",
        "a pair of pincers or claws on the last segment",
        "numerous pairs of legs (one pair per body segment)"
    ],
    "cereal-box": [
        "breakfast cereal branding and logo visible",
        "a top flap or opening mechanism",
        "may include promotional offers or advertisements on the box",
        "typically displayed upright in a standing position",
        "often made of cardboard or similar material"
    ],
    "chandelier-101": [
        "Multiple branches or arms",
        "Often embellished with crystals, glass, or metal elements",
        "Light bulbs or candles at the ends of the arms",
        "Decorative lighting fixture",
        "Suspended from the ceiling"
    ],
    "chess-board": [
        "borders around the board marked with letters (A-H) and numbers (1-8) to indicate specific squares",
        "square board",
        "made from materials like wood, plastic, or vinyl",
        "chess pieces such as pawns, knights, bishops, rooks, queens, and kings",
        "pieces arranged in starting positions or in various stages of gameplay"
    ],
    "chimp": [
        "bare face with expressive eyes",
        "short, stocky build",
        "four-limbed primate",
        "opposable thumbs",
        "visible teeth often due to open mouths in various expressions"
    ],
    "chopsticks": [
        "smooth surface",
        "cylindrical or slightly flattened shape",
        "generally uniform in length and thickness",
        "sometimes decorated with patterns or designs",
        "typically made of wood, bamboo, metal, or plastic"
    ],
    "cockroach": [
        "hard, shiny exoskeleton",
        "prominent cerci (appendages) at the rear",
        "small, oval-shaped body",
        "wings that may lie flat and are sometimes visible",
        "brown or black color"
    ],
    "coffee-mug": [
        "open top for drinking",
        "handle for gripping",
        "sometimes paired with a saucer or coaster",
        "varying colors and designs",
        "cylindrical shape"
    ],
    "coffin": [
        "handles on the sides for carrying",
        "a lid that is often hinged or removable",
        "typically made of wood or metal",
        "a lined interior, often with fabric or padding",
        "decorative elements such as carvings, inlays, or metalwork"
    ],
    "coin": [
        "may have a shiny or dull finish",
        "often contains denomination or currency identifier",
        "made of metal such as gold, silver, copper, or alloy",
        "generally flat with raised or engraved details",
        "edges can be smooth or ridged/serrated"
    ],
    "comet": [
        "elongated tail(s) extending away from the nucleus",
        "bright, glowing nucleus (comet head)",
        "surrounding fuzzy cloud (coma) around the nucleus",
        "the tail(s) often pointed away from the sun due to solar wind; may be straight (ion tail) or curved (dust tail)",
        "usually seen against the backdrop of space or a starry sky"
    ],
    "computer-keyboard": [
        "flat or slightly angled surface",
        "possible presence of additional function keys or media control buttons",
        "usually connected via a cable (USB) or wirelessly (Bluetooth)",
        "often includes a separate numeric keypad on the right",
        "a rectangular shape"
    ],
    "computer-monitor": [
        "Cable connections (power cord, video cables)",
        "Brand logo, often located on the front bezel",
        "Thin bezel or border around the screen",
        "Power button usually located on the front or side",
        "Stand or base to support the screen"
    ],
    "computer-mouse": [
        "optical or laser sensor on the bottom",
        "a cable (for wired mice) or no cable (for wireless mice)",
        "small, handheld input device",
        "typically oval or ergonomically shaped",
        "sometimes additional buttons on the side or top for extra functions"
    ],
    "conch": [
        "intricate ridges or spines along the shell",
        "pointed apex at one end of the shell",
        "often found in marine or tropical settings",
        "flared, wide opening (aperture) at the other end",
        "usually pink, orange, white, or cream-colored interior"
    ],
    "cormorant": [
        "medium-to-large waterbird",
        "vibrant, often blue or green eyes",
        "wings spread out to dry (common posturing)",
        "often seen perched on rocks or posts near water",
        "black or dark brown plumage"
    ],
    "covered-wagon": [
        "the overall appearance of a historic or rustic vehicle",
        "wooden or metal framework",
        "a canvas or cloth cover, often arched over the framework",
        "a driver's seat or bench at the front",
        "four large wheels, typically wooden with spokes"
    ],
    "cowboy-hat": [
        "curved edges on the brim",
        "usually made of felt or straw",
        "often has a chin strap or string",
        "high, creased crown",
        "wide brim"
    ],
    "crab-101": [
        "Crustacean",
        "Prominent mouthparts",
        "Hard exoskeleton",
        "Short tail folded under the body",
        "Stalked eyes"
    ],
    "desk-globe": [
        "often spins or rotates on its axis",
        "blue, green, brown, and other earth tones",
        "sometimes includes a meridian ring (a semi-circular support around the globe)",
        "mounted on a stand or base",
        "spherical shape"
    ],
    "diamond-ring": [
        "additional smaller stones or embellishments on the band (optional)",
        "circular band",
        "central gemstone, typically a diamond",
        "presence of a noticeable shine or reflection from the gemstone and metal band",
        "gemstone often held in place by prongs or a setting"
    ],
    "dice": [
        "black, red, or other colored dots",
        "six faces, each marked with a different number of pips (dots), ranging from 1 to 6",
        "small, cube-shaped object",
        "often made of plastic, wood, or other solid material",
        "typically white or light-colored"
    ],
    "dog": [
        "Variety of colors and patterns (black, white, brown, golden, etc.)",
        "Clawed paws",
        "A tail, which can vary in length and shape",
        "Distinctive snout or muzzle",
        "Typically seen performing various activities like sitting, standing, running, or lying down"
    ],
    "dolphin-101": [],
    "doorknob": [
        "Rounded or spherical shape",
        "Made of metal or other hard materials",
        "Typically mounted on a circular or oval plate",
        "Attached to a door",
        "Can be of various metals including brass, stainless steel, or bronze"
    ],
    "drinking-straw": [
        "various colors or transparent",
        "slender, cylindrical shape",
        "often bends at one end (flexible straws)",
        "hollow structure",
        "relatively small and lightweight"
    ],
    "duck": [
        "Sometimes seen in or near water",
        "Long neck (relative to body size)",
        "Wings that may be folded at its sides",
        "Webbed feet",
        "Distinctive quacking sound (if the photo is part of a video or has an audio aspect)"
    ],
    "dumb-bell": [
        "usually metallic or with a rubber coating",
        "cylindrical or disk-shaped weights",
        "grip area, often textured, in the middle of the bar",
        "available in various colors, often depending on the material or coating",
        "compact and handheld in size"
    ],
    "eiffel-tower": [
        "height distinctive against the skyline",
        "elevated observation decks/platforms",
        "slim spire at the top",
        "lighting at night, often illuminated with golden lights",
        "iconic wrought-iron lattice structure"
    ],
    "electric-guitar-101": [
        "pickups located under the strings",
        "body made of solid or semi-hollow wood",
        "a headstock with tuning pegs",
        "a bridge for anchoring the strings",
        "distinctive shape, often with cutaways for easier access to higher frets"
    ],
    "elephant-101": [
        "Tusks (protruding from the upper jaw, not found in all elephants, more prominent in males)",
        "Small eyes relative to head size",
        "Distinctive, wrinkled skin",
        "Very large, gray or brownish-gray body",
        "Large, floppy ears"
    ],
    "elk": [
        "Muscular build",
        "Small, pointed ears",
        "Dark brown or black snout",
        "Large, four-legged mammal",
        "White tail with a black tip (in some subspecies)"
    ],
    "ewer-101": [
        "often made from materials like metal, ceramic, or glass",
        "tall, narrow body",
        "wide spout for pouring",
        "may have decorative patterns or designs",
        "handle, often ornate or large"
    ],
    "eyeglasses": [
        "often metallic or plastic frames surrounding the lenses",
        "two arms (temples) extending from the lenses to fit over the ears",
        "nose pads or supports where the bridge rests on the nose",
        "two transparent lenses",
        "a pair of lenses held together by a bridge"
    ],
    "fern": [
        "Fronds (feathery leaves) that are often divided into smaller leaflets",
        "Lack of flowers or seeds; reproduces via spores",
        "Green, leafy plant",
        "Rhizomes (horizontal stems that often grow underground)",
        "Symmetrical and patterned leaf arrangement"
    ],
    "fighter-jet": [
        "camouflage or tactical paint scheme",
        "twin tail fins or a single vertical stabilizer",
        "swept-back wings",
        "cockpit canopy that often bulges slightly",
        "sleek, aerodynamic design"
    ],
    "fire-extinguisher": [
        "either mounted on a wall or placed in a fire-extinguisher holder",
        "safety pin or seal to prevent accidental discharge",
        "handle with a lever or trigger for activation",
        "clear labeling or instructions on the body",
        "hose or nozzle attached to the top or side"
    ],
    "fire-hydrant": [
        "sturdy base that is bolted to the ground",
        "valve cap on each nozzle outlet",
        "bright, often vibrant color (commonly red, yellow, or another easily noticeable color)",
        "circular, flanged top that can be removed",
        "multiple nozzle outlets for hose connections"
    ],
    "fire-truck": [
        "large wheels",
        "heavy-duty build",
        "ladders, often extendable",
        "reflective stripes",
        "emergency lights, typically red and blue"
    ],
    "fireworks": [
        "varying colors like red, blue, green, yellow, etc.",
        "patterns such as bursts, streaks, or sparkles",
        "bright, colorful explosions in the sky",
        "crowds of people watching, often with upturned faces",
        "trails of light or sparks leading from the ground into the sky"
    ],
    "flashlight": [
        "possible brand markings or logos",
        "a bulb or LED light source visible through the lens",
        "a switch or button to turn it on or off",
        "cylindrical or handheld shape",
        "a clear lens at one end"
    ],
    "floppy-disk": [
        "made of plastic",
        "a label area for writing or printing information",
        "small, square, or rectangular object",
        "flexible magnetic disk encased in a hard plastic shell",
        "size typically 3.5 inches or 5.25 inches"
    ],
    "football-helmet": [
        "team logos or colors on the exterior shell",
        "ventilation holes or openings",
        "faceguard made of metal bars",
        "padding inside the helmet for protection",
        "ear holes for hearing"
    ],
    "french-horn": [
        "intricate tubing that often loops around multiple times",
        "three or more rotary valves",
        "a mouthpiece attached to the narrow end",
        "often held by the player with their hand in the bell",
        "circular coils of tubing"
    ],
    "fried-egg": [
        "edges of the egg white might be crispy or slightly browned",
        "slightly raised yolk from the flat egg white",
        "bright yellow yolk, often in the center",
        "white, round or oval egg white",
        "may be accompanied by breakfast items like toast, bacon, or vegetables"
    ],
    "frisbee": [
        "may have brand logos or designs on the surface",
        "made of plastic or a similar material",
        "smooth, round edges",
        "often brightly colored or with distinctive patterns",
        "flat and disc-like"
    ],
    "frog": [
        "wide mouth",
        "smooth or bumpy skin",
        "webbed feet",
        "visible eardrums (tympanic membranes) on the sides of the head",
        "bulging eyes on top of the head"
    ],
    "frying-pan": [
        "sometimes includes a lid or protective cover",
        "relatively shallow sides",
        "consists of materials like stainless steel, cast iron, or non-stick surfaces",
        "often black or silver in color",
        "long handle attached to one side"
    ],
    "galaxy": [
        "various colors, often including shades of blue, white, and yellow",
        "sometimes accompanied by satellite galaxies",
        "a bright central core or bulge",
        "diffuse, luminous cloud-like appearance",
        "dust lanes or bands of darker material"
    ],
    "gas-pump": [
        "Tall structure with a digital or mechanical display showing prices and quantities",
        "Often situated on a pump island for vehicle access",
        "Fuel dispensing hose attached to the main structure",
        "Often features branding or logos of fuel companies",
        "Buttons or touch screen interface for selecting fuel grade and payment options"
    ],
    "giraffe": [
        "distinctive coat pattern with irregular brown patches separated by lighter lines",
        "small, rounded ears",
        "long, prehensile tongue",
        "relatively short tail with a tuft of hair at the end",
        "mane running along the neck"
    ],
    "goat": [
        "medium-sized horns that curve backward",
        "four-legged mammal",
        "a short tail that may be upward or straight",
        "a beard, typically found on males",
        "usually covered in coarse fur, which can be white, brown, black, or a mix of colors"
    ],
    "golden-gate-bridge": [
        "vertical suspender cables connecting the main cable to the bridge deck",
        "long main span supported by cables",
        "international orange color",
        "pedestrian walkways on either side",
        "often shrouded in fog or with a background of the city skyline"
    ],
    "goldfish": [
        "pectoral and pelvic fins near the body",
        "two long, flowing dorsal fins",
        "transparent or slightly opaque fins",
        "small, aquatic animal",
        "found in a water environment, such as an aquarium or pond"
    ],
    "golf-ball": [
        "covered in dimples (small indentations)",
        "standard size approximately 1.68 inches (42.67 mm) in diameter",
        "may have brand names or logos printed on it",
        "small, spherical object",
        "typically white or sometimes colored"
    ],
    "goose": [
        "webbed feet",
        "often seen near water or in open fields",
        "flat, broad bill",
        "broad wings",
        "long neck"
    ],
    "gorilla": [
        "bare-faced with prominent brow ridges",
        "pronounced jaw and large canines",
        "large and robust primate",
        "large hands and feet with opposable thumbs and big toes",
        "visible chest and abdominal areas with less fur"
    ],
    "grand-piano-101": [
        "three or more legs, often with decorative detailing",
        "large, wooden body",
        "a lyre-shaped pedal assembly with two or three pedals",
        "an elevated music stand for holding sheet music",
        "strings and hammers visible inside when the lid is open"
    ],
    "grapes": [
        "small, round or oval-shaped fruits",
        "often found on vine branches or in a bowl",
        "attached to thin stems",
        "typically green, red, purple, or black in color",
        "may have a slight sheen or gloss"
    ],
    "grasshopper": [
        "strong hind legs adapted for jumping",
        "long, slender antennae",
        "tough, chitinous exoskeleton",
        "relatively short front legs",
        "typically green or brown in color"
    ],
    "guitar-pick": [
        "typically made of plastic, but can also be metal, wood, or other materials",
        "varying thickness (thin to thick)",
        "often solid-colored, but may also have graphics, logos, or text",
        "approximately the size of a coin, fitting easily between the fingers",
        "smooth or textured surface"
    ],
    "hamburger": [
        "sesame seeds on the top bun (optional)",
        "layers of vegetables such as lettuce, tomato, and onion",
        "round bun (top and bottom halves)",
        "cooked beef patty",
        "condiments like ketchup, mustard, or mayonnaise"
    ],
    "hammock": [
        "Curved or sagging shape when in use",
        "Often made of cloth or woven material",
        "Straps, ropes, or cords for hanging",
        "Sometimes includes a spreader bar that keeps the fabric open",
        "Typically found in outdoor settings like gardens, beaches, or camping sites"
    ],
    "harmonica": [
        "shiny, metallic surface",
        "cover plates on top and bottom with screws on the sides",
        "rectangular, compact shape",
        "often has a brand name or logo etched on the cover",
        "typically small enough to fit in one hand"
    ],
    "harp": [
        "curved, upright column",
        "pedals at the base (for larger pedal harps)",
        "intricate decorative designs (often on the column or soundboard)",
        "large, stringed musical instrument",
        "multiple strings extending diagonally"
    ],
    "harpsichord": [
        "a large, rectangular body",
        "one or more sets of strings, sometimes visible through a latticework cover",
        "ornate legs or stand",
        "decorative carvings or paintings, often present on the case and lid",
        ""
    ],
    "hawksbill-101": [
        "marine turtle",
        "two claws on each flipper",
        "shell color ranges from amber to brown with streaks of yellow, black, and gold",
        "narrow, pointed beak resembling a hawk's bill",
        "medium size compared to other sea turtles"
    ],
    "head-phones": [
        "audio accessory",
        "brand logos or labels (sometimes)",
        "cushioning or padding on the ear cups (over-ear/on-ear types)",
        "adjustable headband (for some types)",
        "a headband (over-ear/on-ear types) or connecting wire (in-ear types)"
    ],
    "helicopter-101": [
        "Engine exhaust ports",
        "Rotating main rotor blades on top",
        "Landing skids or wheels",
        "May have auxiliary structures such as external fuel tanks or equipment mounts",
        "An elongated fuselage (body)"
    ],
    "hibiscus": [
        "Serrated leaf edges",
        "Often found as shrubs or small trees",
        "Brightly colored petals (commonly red, pink, orange, yellow, or white)",
        "Glossy, dark green leaves",
        "Prominent central staminal column (long, tube-like structure in the middle of the flower)"
    ],
    "homer-simpson": [
        "Large, round eyes",
        "Wearing a short-sleeved white collared shirt",
        "Often depicted with a stubbly beard",
        "Blue pants",
        "Overweight with a prominent belly"
    ],
    "horse": [
        "Long neck",
        "Hooves on each foot",
        "Large, expressive eyes",
        "Pointed ears that can move independently",
        "Mane along the top of the neck"
    ],
    "horseshoe-crab": [
        "relatively flat body",
        "dome-shaped, horseshoe-like shell",
        "compound eyes on top of the shell",
        "book gills on the underside near the back",
        "pincers at the end of some legs"
    ],
    "hot-air-balloon": [
        "rounded, bulbous shape when fully inflated",
        "basket or gondola hanging below the balloon",
        "may have passengers or pilot inside the basket",
        "often seen in open areas or during events like balloon festivals",
        "vertical ropes or cables connecting the basket to the envelope"
    ],
    "hot-dog": [
        "can be seen with side items like fries or a drink  ",
        "elongated sausage  ",
        "often held horizontally ",
        "condiments like mustard, ketchup, relish, or onions on top ",
        "sausage usually held in a soft, split bread roll  "
    ],
    "hot-tub": [
        "filled with water",
        "steps leading up to the tub",
        "large, often circular or rectangular basin",
        "visible jets or bubbles",
        "steam rising from the water, indicating heat"
    ],
    "hourglass": [
        "fine grains flowing from the upper to the lower chamber",
        "an upper and a lower chamber ",
        "wooden, metal, or plastic frame holding the glass bulbs in place",
        "two glass bulbs connected by a narrow neck",
        "usually symmetric design"
    ],
    "house-fly": [
        "pair of transparent wings",
        "four distinct black stripes on the thorax",
        "small, usually about 5-8 mm long",
        "distinct vein patterns on the wings",
        "segmented antennae"
    ],
    "human-skeleton": [
        "long bones in arms (humerus, radius, ulna)",
        "long bones in legs (femur, tibia, fibula)",
        "rib cage surrounding chest area",
        "typically an upright or lying down position",
        "pelvis with hip bones"
    ],
    "hummingbird": [
        "Rapid wing movement (wings often appear blurred in photos)",
        "Iridescent plumage (often brightly colored)",
        "Very small size",
        "Perching on thin branches or near flowers",
        "Relatively short tail"
    ],
    "ibis-101": [],
    "ice-cream-cone": [
        "various colors and flavors of ice cream",
        "possible toppings such as sprinkles, nuts, or syrup",
        "often held in hand or presented in a holder",
        "scoops of ice cream on top",
        "conical wafer or sugar cone"
    ],
    "iguana": [
        "four-limbed reptile",
        "a stout body with powerful limbs",
        "predominantly green or brown color, sometimes with stripes or spots",
        "a row of spines running down the back and tail",
        "a long tail, often with distinctive banding or coloration"
    ],
    "ipod": [
        "control buttons (play/pause, volume, forward/backward)",
        "earbud or headphone port",
        "sleek, polished exterior, often with a metallic or plastic finish",
        "compact, rectangular shape",
        "USB or dedicated charging port"
    ],
    "iris": [],
    "jesus-christ": [
        "Depictions with symbolic elements such as a cross, lamb, or fish",
        "Long hair, often depicted as wavy or curly",
        "Often shown in serene or divine settings, like in heaven, a church, or nature with bright light",
        "Crucifixion wounds on hands, feet, and side (stigmata)",
        "Beard, usually full and neatly groomed"
    ],
    "joy-stick": [
        "a cord for connecting to a computer or console (wireless models may lack this)",
        "handheld control device",
        "base with buttons and/or trigger",
        "usually made of plastic",
        "vertical stick or handle"
    ],
    "kangaroo-101": [
        "Small head with large ears",
        "Strong hind legs",
        "Large marsupial",
        "Brown or grey fur",
        "Large feet"
    ],
    "kayak": [
        "small, enclosed cockpit for one or two people",
        "may have deck lines or bungee cords on top",
        "pointed ends on both sides",
        "occasionally features foot rests or rudder system",
        "narrow and elongated shape"
    ],
    "ketch-101": [],
    "killer-whale": [
        "paddle-shaped pectoral fins",
        "tall, triangular dorsal fin",
        "distinctive black and white coloration",
        "large, marine mammal",
        "streamlined, robust body"
    ],
    "knife": [
        "a pointed tip (though some may have a rounded tip)",
        "sometimes a bolster (the thick junction between the handle and the blade)",
        "",
        "a tang (the part of the blade extending into the handle)",
        "various shapes and sizes depending on the type (e.g., chef's knife, paring knife, bread knife, etc.)"
    ],
    "ladder": [
        "Series of horizontal rungs or steps",
        "Elongated structure",
        "Can be made of materials like wood, aluminum, or fiberglass",
        "May be a fixed-length or an extendable type (e.g., extension ladder)",
        "Stabilizing feet or pads at the base"
    ],
    "laptop-101": [
        "Power button",
        "Charging port",
        "Speakers",
        "USB ports",
        "Thin, foldable design with a hinge"
    ],
    "lathe": [
        "Chuck or collet holding the workpiece",
        "A rotating spindle or headstock",
        "Industrial machine",
        "Carriage or cross slide mechanism for moving the tool post",
        "Safety guards or shields covering moving parts"
    ],
    "leopards-101": [
        "Fur covered in distinctive spots called rosettes",
        "Large cat with a sleek, muscular build",
        "Green or blue eyes",
        "Yellow to gold-colored coat",
        "Long tail"
    ],
    "license-plate": [
        "typically mounted on the front or rear of a vehicle",
        "standardized size for vehicles in a given region",
        "may have regional, state, or country-specific designs or logos",
        "bordered by a frame",
        "reflective or metallic surface"
    ],
    "lightbulb": [
        "Pear-shaped, tubular, or globe-shaped bulb",
        "Transparent or translucent glass or plastic bulb",
        "Emitter of light when turned on",
        "Metal base with a screw or pin configuration",
        "Often smaller in size compared to other objects"
    ],
    "light-house": [
        "usually located near coastlines, on cliffs, or on rocky outcrops",
        "a rotating or flashing light",
        "a lantern room at the top",
        "painted in distinct patterns or bright colors (often white with red or black)",
        "surrounding maritime environment (water, sea, rocky shores)"
    ],
    "lightning": [
        "illumination of surrounding clouds",
        "occurs in the sky, often against a backdrop of dark clouds",
        "can sometimes be accompanied by rain or stormy weather elements",
        "branching pattern",
        "strikes intensely bright areas and fades quickly"
    ],
    "llama-101": [],
    "mailbox": [
        "varying colors, but commonly red, black, or white",
        "may have a flag (usually red) for outgoing mail",
        "rectangular or cylindrical shape",
        "typically made of metal or plastic",
        "a slot or opening for mail insertion"
    ],
    "mandolin": [
        "teardrop or oval-shaped body",
        "often features decorative inlays or bindings",
        "soundhole (usually in an \"f\" shape or oval)",
        "wooden construction",
        "a headstock often with tuning pegs"
    ],
    "mars": [
        "large, noticeable volcanoes such as Olympus Mons",
        "surface with numerous craters",
        "thin atmosphere, often giving a clear view of the surface",
        "reddish or rusty color ",
        "white polar ice caps"
    ],
    "mattress": [
        "visible layers or seams, especially on the sides",
        "generally covered in fabric or a mattress cover",
        "can appear as a single or a stack in various settings like bedrooms or retail displays",
        "may have handles on the sides",
        "typically white, cream, or light-colored"
    ],
    "megaphone": [
        "sometimes a shoulder strap or carrying handle",
        "often brightly colored, commonly white, red, or blue",
        "made of plastic or metal materials",
        "a narrower handle on the other end",
        "a visible speaking mouthpiece at the narrow end"
    ],
    "menorah-101": [
        "Base or stand supporting the branches",
        "Central raised branch (shamash) on a Hanukkiah",
        "Candle holders or oil cups at the top of each branch",
        "Ornate designs, sometimes with Jewish symbols such as the Star of David",
        "Often made of metal (silver or gold) or other materials like wood or ceramic"
    ],
    "microscope": [
        "a stage for placing samples",
        "mechanical stage controls (for precise movement of the sample)",
        "a light source or mirror for illumination",
        "sometimes connected to devices like a computer or camera",
        "arm or frame connecting the base to the eyepiece"
    ],
    "microwave": [
        "usually rectangular in shape",
        "control panel with buttons or a digital display",
        "turntable or flatbed inside the cavity",
        "interior cavity for placing food",
        "door with a transparent or semi-transparent window"
    ],
    "minaret": [
        "balconies or galleries",
        "decorative elements like arches, carvings, and tiles",
        "conical or onion-shaped top",
        "typically attached to or near a mosque",
        "tall, slender tower"
    ],
    "minotaur": [
        "aggressive or fearsome appearance",
        "sometimes holding weapons like an axe or club",
        "cloven hooves or human feet",
        "human-like body",
        "often depicted with fur, especially around the head and upper torso"
    ],
    "motorbikes-101": [
        "Saddle-style seat",
        "Headlight and taillight",
        "Wheels with visible tires and spokes (or mag wheels)",
        "Footrests or footpegs",
        "Exhaust pipe"
    ],
    "mountain-bike": [
        "often features a water bottle holder and/or attachments for additional gear",
        "thick, knobby tires for off-road traction",
        "chain and pedals",
        "disc or V-brakes",
        "gear shifters and multiple gears"
    ],
    "mushroom": [
        "Cap (umbrella-like top part)",
        "Various colors and textures on the cap",
        "Absence of leaves or branches",
        "Gills or pores on the underside of the cap",
        "Typically growing close to the ground"
    ],
    "mussels": [
        "bivalve shell",
        "often found clustered together in groups",
        "dark-colored shell, often black, dark blue, or brown",
        "interior of the shell has a shiny, pearly surface",
        "elongated oval shape"
    ],
    "necktie": [
        "tied in a knot at the neck",
        "usually made of silk, polyester, or cotton",
        "positioned under a shirt collar",
        "long, narrow fabric",
        "pointed or squared ends"
    ],
    "octopus": [
        "a beak located where the arms converge",
        "eight long, flexible arms with suction cups",
        "two large, prominent eyes",
        "the ability to change color and texture",
        "soft, bulbous head (mantle)"
    ],
    "ostrich": [
        "Prominent, rounded body",
        "Long neck with sparse feathers",
        "Swift, two-toed feet",
        "Tall and long-legged",
        "Large, flightless bird"
    ],
    "owl": [
        "rounded head without a prominent neck",
        "facial disk (concentric circles of feathers around the eyes)",
        "upright posture",
        "taloned feet",
        "sharp, hooked beak"
    ],
    "palm-pilot": [
        "physical buttons below or alongside the screen",
        "relatively compact size compared to modern smartphones",
        "logo or branding (often \"Palm\")",
        "rectangular shape",
        "ports for syncing and charging"
    ],
    "palm-tree": [
        "no branches along the trunk, only at the top",
        "typically found in tropical or subtropical environments",
        "long, feather-like or fan-shaped leaves (fronds)",
        "leaves can be green or yellowish",
        "leafy crown at the top of the trunk"
    ],
    "paperclip": [
        "open ends to hold papers together",
        "looped or twisted shape",
        "elongated, oval or rectangular form",
        "typically silver, though available in various colors",
        "metal or plastic material"
    ],
    "paper-shredder": [
        "electronic or manual device",
        "an attached bin or container for collecting shredded paper",
        "visible shredder blades or cutters inside the slot (sometimes visible)",
        "often in colors like black, grey, or white",
        "a slot for feeding paper at the top"
    ],
    "pci-card": [
        "Gold-plated edge connector fingers",
        "Capacitors and resistors",
        "PCI connector notch that aligns with motherboard slot",
        "Various integrated circuits (chips)",
        "Labeled components and model numbers"
    ],
    "penguin": [
        "webbed feet",
        "a distinct beak, usually short and pointed",
        "short, stubby wings or flippers",
        "a short, thick neck",
        "upright, bipedal stance"
    ],
    "people": [
        "Presence of hands and feet",
        "Clothing",
        "Varying skin tones",
        "Facial features such as eyes, nose, and mouth",
        "Standing, sitting, or various other postures"
    ],
    "pez-dispenser": [
        "A flap or opening mechanism at the stem's front for dispensing candy",
        "Clear horizontal section dividing the stem and the head",
        "Candy tablets stacked inside the stem",
        "Compact size, usually handheld",
        "A character or decorative head on top of the stem (often depicting popular characters or themes)"
    ],
    "photocopier": [
        "power cord",
        "paper input tray or feeder",
        "often situated on small wheeled base or stand",
        "a lid that lifts to reveal the glass scanning surface",
        "control panel with buttons and/or a touchscreen"
    ],
    "picnic-table": [
        "typically has a rustic or utilitarian design",
        "may be accompanied by an umbrella or shade structure",
        "rectangular or square table surface",
        "attached bench seats along either side",
        "legs or support structures connecting table and benches"
    ],
    "playing-card": [
        "symmetric design",
        "standardized size (approximately 2.5 inches by 3.5 inches)",
        "usually made of paper or plastic",
        "a front side with numbers, symbols, or images (such as hearts, diamonds, clubs, spades, or face cards with kings, queens, and jacks)",
        "often white or light-colored background on the front"
    ],
    "porcupine": [
        "Rodent-like body",
        "Rounded body shape",
        "Clawed feet for climbing (if it\u2019s a tree-dwelling species)",
        "Generally brown, black, or grey fur interspersed with quills",
        "Short legs"
    ],
    "pram": [
        "push handle",
        "wheeled vehicle",
        "large, often sturdy wheels",
        "seat or bassinet for carrying an infant",
        "storage basket or tray below the seat"
    ],
    "praying-mantis": [
        "large, compound eyes",
        "two antennae",
        "folded wings (if adult) that can often be hard to see when the insect is at rest",
        "raptorial (grasping) front legs held in a \"praying\" position",
        "triangular head"
    ],
    "pyramid": [
        "typically associated with desert or arid landscapes (e.g., sand, sparse vegetation)",
        "large, often monumental in scale",
        "made of stone, bricks, or similar materials",
        "often found in the context of archaeological sites or among smaller ruins",
        "sloping triangular faces that converge to a point at the top (the apex)"
    ],
    "raccoon": [
        "medium-sized mammal",
        "pointed snout",
        "stocky body",
        "ringed tail with alternating dark and light bands",
        "distinctive \"mask\" of black fur around the eyes"
    ],
    "radio-telescope": [
        "supporting structure or mount holding the dish",
        "sometimes multiple antennas arranged in an array",
        "metal or composite reflective surface",
        "infrastructure for signal collection and processing",
        "often located in an open field or elevated area"
    ],
    "rainbow": [
        "appears after rain or in the presence of water droplets and sunlight",
        "curved arc shape in the sky",
        "multiple distinct bands of color (commonly red, orange, yellow, green, blue, indigo, and violet)",
        "often appears semi-transparent",
        "sometimes accompanied by a secondary, fainter rainbow outside the primary arc"
    ],
    "refrigerator": [
        "cooling vents or panels",
        "typically white, silver, or black in color",
        "compartments and shelves when the doors are open",
        "doors (one or two) that swing open",
        "large appliance"
    ],
    "revolver-101": [
        "A short to medium-length barrel",
        "A trigger mechanism",
        "A hammer that is used to strike the primer of the cartridge",
        "A cylindrical chamber that holds ammunition, typically visible ",
        "Often metallic, with finishes such as black, silver, or blued steel"
    ],
    "rifle": [
        "buttstock (the rear part of the rifle)",
        "magazine or chamber for ammunition",
        "long, cylindrical barrel",
        "visible mechanical components such as bolts, levers, and safety switches",
        "stock (which may be wooden, synthetic, or metal)"
    ],
    "rotary-phone": [
        "Usually a sturdy, boxy base",
        "Mechanical rotary mechanism",
        "Often made of plastic or Bakelite materials",
        "Numbering around the dial, typically from 0 to 9",
        "Handset with a mouthpiece and earpiece"
    ],
    "roulette-wheel": [
        "numbers arranged in a specific sequence (non-consecutive order)",
        "a central hub where the wheel spins",
        "alternating colors (usually red and black, sometimes green for zero)",
        "numbered pockets",
        "a betting layout table usually adjacent to the wheel"
    ],
    "saddle": [
        "leather or synthetic material",
        "saddle flaps or skirts on the sides",
        "some may have decorative elements like stitching or tooling",
        "girth or cinch straps to secure it to the horse",
        "curved seat with a raised front (pommel) and back (cantle)"
    ],
    "saturn": [],
    "school-bus": [
        "flashing red or yellow lights on the top and sides",
        "stop sign arm on the side",
        "multiple doors, usually one at the front and sometimes one at the rear",
        "large, rounded front hood and cab (for North American conventional school buses)",
        "\"SCHOOL BUS\" signage on the top front and rear"
    ],
    "scorpion-101": [],
    "screwdriver": [
        "handheld tool",
        "compact size, fitting easily in one hand",
        "a metal blade extending from the handle",
        "a long, cylindrical shaft",
        "sometimes colored or labeled handles (e.g., red for flathead, blue for Phillips)"
    ],
    "segway": [
        "controls or display screen on the handlebar",
        "grip handles on the handlebar",
        "two parallel wheels",
        "upright, self-balancing vehicle",
        "may have fenders over the wheels"
    ],
    "self-propelled-lawn-mower": [
        "adjustable cutting height settings",
        "four wheels",
        "a grass collection bag or side-discharge chute",
        "an engine mounted on top of the deck",
        "a handlebar"
    ],
    "sextant": [
        "Nautical instrument",
        "Vernier scale or micrometer drum for precise measurements",
        "Circular handle or grip",
        "Mirrors (index mirror and horizon mirror)",
        "Telescope or sighting mechanism"
    ],
    "sheet-music": [
        "white or light-colored paper",
        "clefs (such as the treble or bass clef)",
        "horizontal staves with five lines each",
        "musical notes and symbols",
        "flat pages or booklets"
    ],
    "skateboard": [
        "attached to two trucks (axles) under the deck",
        "kicktails (upward curves) at one or both ends of the deck",
        "grip tape on the top surface of the deck",
        "the deck often has artistic designs or logos",
        "a flat, elongated deck"
    ],
    "skunk": [
        "pointed snout",
        "small, rounded ears",
        "small to medium size",
        "short legs with clawed feet",
        "bushy tail, often with white fur"
    ],
    "skyscraper": [
        "multiple stories (often dozens or more)",
        "modern architectural design",
        "large windows or glass facades",
        "steel framework or reinforced concrete structure",
        "appears significantly taller compared to surrounding buildings"
    ],
    "smokestack": [
        "emits smoke, steam, or exhaust gases",
        "often extends high above buildings or surrounding landscape",
        "tall structure, often cylindrical",
        "can have a conical or straight top",
        "sometimes marked with warning lights or paint stripes"
    ],
    "snail": [
        "small, soft-bodied invertebrate",
        "two pairs of tentacles: upper pair with eyes, lower pair for feeling",
        "typically found on leaves, soil, or near water",
        "tentacles or feelers on its head",
        "coiled shell on its back"
    ],
    "snake": [
        "wide, flattened head that may be distinct from the neck",
        "scaly skin",
        "elongated, cylindrical body",
        "no external ears",
        "variable coloration and patterns (can be solid, striped, or patterned)"
    ],
    "sneaker": [
        "Made of fabric, leather, or synthetic materials",
        "Sometimes colorful or with stylish patterns",
        "Low-top, mid-top, or high-top variations",
        "Athletic footwear",
        "Lace-up closure or Velcro straps"
    ],
    "snowmobile": [
        "headlights at the front",
        "identifiable brand logos or markings",
        "a windshield (often small)",
        "skis at the front for steering",
        "usually designed to sit low to the ground"
    ],
    "soccer-ball": [
        "inflation valve (small circular hole, usually with a rubber or plastic covering)",
        "size often comparable to a basketball, but with a distinctive pattern and texture",
        "typically black and white pentagon and hexagon patterns, though it can come in various colors and designs",
        "visible stitching or panels",
        "textured surface made of leather or synthetic material"
    ],
    "socks": [
        "Heel and toe sections",
        "Tubular shape with a closed end",
        "Footwear accessory",
        "Varied in color and patterns",
        "Often ribbed or elasticated cuff at the top"
    ],
    "soda-can": [
        "made of metal, typically aluminum",
        "often found in groups (e.g., packs or vending machines)",
        "a pop-top or pull-tab opening",
        "relatively small size, usually 12 fluid ounces (355 milliliters) or less",
        "may have nutritional information and barcodes printed on the side"
    ],
    "spaghetti": [
        "usually served on a plate or in a bowl",
        "yellow or off-white color when uncooked",
        "long, thin pasta noodles",
        "often served with sauce, which can be red (tomato-based), white (cream-based), or green (pesto)",
        "may be accompanied by utensils such as a fork or spoon"
    ],
    "speed-boat": [
        "a pointed bow (front) and a wider stern (back)",
        "a control console with a steering wheel and throttle controls",
        "often brightly colored or with sporty graphics",
        "sleek and aerodynamic design",
        "one or more powerful outboard or inboard motors"
    ],
    "spider": [
        "No antennae",
        "Multiple eyes, usually arranged in patterns",
        "Arachnid with eight legs",
        "Two main body segments (cephalothorax and abdomen)",
        "Fangs or chelicerae near the mouth"
    ],
    "spoon": [
        "typically slim and slender form",
        "reflective surface if metallic",
        "elongated handle",
        "the handle may have engravings or designs",
        "the bowl usually has a smooth, curved interior"
    ],
    "stained-glass": [
        "light shining through the glass, creating a radiant effect",
        "depiction of scenes, figures, or abstract forms",
        "visible framing or support structure for the glass",
        "often found in windows, especially in churches and historic buildings",
        "intricate patterns or designs"
    ],
    "starfish-101": [
        "presence of a central mouth on the underside",
        "typically has a star-like shape",
        "underside has tube-like feet for movement",
        "marine invertebrate",
        "colors can vary, often including shades of red, orange, yellow, brown, or even blue"
    ],
    "steering-wheel": [
        "attached to a steering column",
        "circular or semi-circular shape",
        "control buttons or dials mounted on the wheel",
        "usually positioned in front of the driver's seat",
        "textured or grip-friendly rim"
    ],
    "stirrups": [
        "Shaped to hold a rider's foot",
        "Oval or triangular in shape",
        "Attached to straps or leathers",
        "Usually positioned on either side of a saddle",
        "Metal or synthetic loops"
    ],
    "sunflower-101": [
        "typically faces towards the sun",
        "large, round flower head",
        "yellow petals",
        "can reach significant heights (up to several feet tall)",
        "rough, hairy stem"
    ],
    "superman": [
        "muscular build",
        "red boots",
        "iconic blue suit",
        "red cape",
        "often seen flying or in an action pose"
    ],
    "sushi": [
        "vegetables like cucumber, avocado, or radish",
        "soy sauce, wasabi, and pickled ginger often present as accompaniments",
        "raw or cooked fish, such as salmon, tuna, or shrimp",
        "garnishes, such as sesame seeds, fish roe, or sliced green onions",
        "rice, often shaped into small mounds or rolls"
    ],
    "swan": [
        "elegant posture",
        "webbed feet",
        "white or black plumage",
        "elongated neck",
        "long wings"
    ],
    "swiss-army-knife": [
        "Multiple fold-out tools such as blades, screwdrivers, and bottle openers",
        "Compact, rectangular shape",
        "Metal components, typically stainless steel",
        "Rivets or hinges along the handle for tool articulation",
        "Red or dark-colored handle, often with a logo featuring a white cross on a shield"
    ],
    "sword": [
        "elongated blade",
        "sharp or pointed tip",
        "often symmetrical design",
        "may have a scabbard (protective sheath)",
        "often metallic (shiny or reflective surface)"
    ],
    "syringe": [
        "cylindrical body (often transparent)",
        "typically small and handheld",
        "needle attached to one end, often covered with a protective cap",
        "plunger that fits inside the cylinder",
        "measurement markings along the side"
    ],
    "tambourine": [
        "typically has an open back",
        "handheld size",
        "may have a grip or handle on the frame",
        "circular frame",
        "a drumhead (sometimes present, sometimes not)"
    ],
    "teapot": [
        "sometimes features decorative designs or patterns",
        "vessel typically made of ceramic, metal, or glass",
        "round or oval body",
        "a lid, often with a small knob, that covers the opening",
        "a handle for holding"
    ],
    "teddy-bear": [
        "round ears",
        "sewn-in or button eyes",
        "often comes with accessories like a bow tie, ribbon, or clothing",
        "stuffed toy",
        "typically brown, but can be other colors like white, tan, or even bright colors"
    ],
    "teepee": [
        "conical shape",
        "ropes or bindings holding the poles together",
        "entrance flap at the base",
        "sometimes decorated with paintings or patterns",
        "often set up in a natural outdoor setting"
    ],
    "telephone-box": [
        "often includes signage indicating it is a phone booth (e.g., 'TELEPHONE' sign)",
        "traditional models are red (e.g., classic British telephone boxes) or other noticeable colors",
        "a keypad or rotary dial on older models",
        "a telephone handset inside, typically connected by a cord",
        "enclosed structure, often with transparent windows"
    ],
    "tennis-ball": [
        "bright yellow or neon green color",
        "fuzzy or felt-like outer texture",
        "approximately 6.7 cm (2.63 inches) in diameter",
        "seam running around the circumference in a curved, \"X\" or \"infinite\" pattern",
        "small spherical object"
    ],
    "tennis-court": [
        "Green, blue, or red surface (commonly)",
        "Tennis posts with net in the middle",
        "Scoreboards (optional)",
        "Net dividing the court into two halves",
        "Rectangular shape with marked boundary lines"
    ],
    "tennis-racket": [
        "often has a logo or brand name on the strings or frame",
        "oval or circular frame",
        "string bed is strung with tension",
        "interwoven strings forming a net within the frame",
        "elongated handle with grip"
    ],
    "theodolite": [
        "telescope mounted on a rotating platform",
        "level bubbles or a digital display",
        "graduated horizontal and vertical circles (for measuring angles)",
        "eyepiece for viewing through the telescope",
        "surveying instrument"
    ],
    "toaster": [
        "a lever or push-down mechanism",
        "heat or toasting elements inside the slots (occasionally visible)",
        "crumb tray at the bottom (sometimes visible from certain angles)",
        "typically made of metal or plastic",
        "control knobs or buttons for adjusting browning settings"
    ],
    "tomato": [
        "round or slightly oval shape",
        "smooth skin",
        "green leafy stem or calyx at the top",
        "sometimes showing a slight sheen",
        "red, green, yellow, or orange color"
    ],
    "tombstone": [
        "often found in a cemetery or graveyard setting",
        "religious symbols (e.g., crosses, stars of David)",
        "engraved text or inscriptions",
        "decorative carvings or motifs",
        "names, dates of birth, and death"
    ],
    "top-hat": [
        "tall and cylindrical shape",
        "flat crown (top)",
        "commonly black, but can also be seen in other colors",
        "usually made from felt, silk, or wool",
        "often has a ribbon or band around the base of the crown"
    ],
    "touring-bike": [
        "front and rear racks for carrying panniers or bags",
        "longer wheelbase for stability and comfort",
        "sturdy frame, often with a larger and more robust build",
        "drop handlebars for various hand positions",
        "wider tires compared to standard road bikes"
    ],
    "tower-pisa": [
        "located in an open area, often with greenery or other historic buildings nearby",
        "the top-level has a belfry (bell chamber) with smaller arches",
        "distinctive lean to one side",
        "freestanding bell tower",
        "circular base and series of columns around each level"
    ],
    "traffic-light": [
        "positioned at intersections or pedestrian crossings",
        "rectangular or box-like housing",
        "typically three lights (red, yellow, green)",
        "vertical or horizontal pole or frame",
        "circular light lenses"
    ],
    "treadmill": [
        "power cord",
        "safety key or clip often attached to the panel",
        "incline settings often visible",
        "side platform/deck beside the belt",
        "handrails or side bars"
    ],
    "triceratops": [
        "a large, robust body",
        "often depicted in a prehistoric or natural landscape setting",
        "large bony frill at the back of the head",
        "rough, scaly skin",
        "four sturdy legs with hooved toes"
    ],
    "tricycle": [
        "sometimes a basket or storage area at the back",
        "a low center of gravity",
        "sometimes colorful and designed for children",
        "three wheels",
        "pedals typically located near the front wheel"
    ],
    "trilobite-101": [
        "Head shield (cephalon) with facial sutures",
        "Typically an elongated, oval shape",
        "Tail shield (pygidium)",
        "Exoskeleton with rib-like structures (pleurae)",
        "Segmented body with three distinct lobes (left pleural lobe, central axial lobe, right pleural lobe)"
    ],
    "tripod": [
        "often made of metal, carbon fiber, or plastic",
        "central column or pole",
        "three-legged structure",
        "locking mechanisms on the legs or head",
        "sometimes includes a handle or lever for adjusting the head"
    ],
    "t-shirt": [
        "often has graphics, logos, or text on the front or back",
        "short sleeves",
        "generally loose-fitting and casual in style",
        "comes in various colors and patterns",
        "no buttons or zippers"
    ],
    "tuning-fork": [
        "sleek, smooth surface",
        "U-shaped metal fork",
        "a round handle or stem at the base of the fork",
        "prongs often have a rounded end",
        "two prongs (tines) extending parallel from a base"
    ],
    "tweezer": [
        "arms connected at one end, creating a pincer-like mechanism",
        "typically silver, black, or brightly colored",
        "pointed, slanted, or flat tips",
        "sometimes has a textured grip for better handling",
        "small, handheld tool"
    ],
    "umbrella-101": [
        "Handle at the bottom of the shaft (may be curved or straight)",
        "Long, central shaft (often metal or wood)",
        "Collapsible mechanism (may be manual or automatic)",
        "Tip at the top of the shaft",
        "Spokes or ribs extending from the shaft to support the canopy"
    ],
    "unicorn": [
        "typically depicted in fantasy or mythical settings",
        "a single, spiraled horn on its forehead",
        "often surrounded by a magical or ethereal aura",
        "often depicted with a flowing mane and tail",
        "frequently depicted in white or other bright colors"
    ],
    "vcr": [
        "buttons and controls on the front panel (e.g., play, stop, rewind)",
        "rectangular electronic device",
        "LED or digital display panel showing time or status",
        "front-loading cassette slot (for VHS tapes)",
        "input and output ports on the back (e.g., RCA connectors)"
    ],
    "video-projector": [
        "lens or multiple lenses on the front",
        "adjustable focus ring or buttons near the lens",
        "control buttons or a small control panel on the top or sides",
        "cooling vents or fans on the sides or back",
        "compact, box-like structure"
    ],
    "washing-machine": [
        "a detergent drawer (often for front-loading machines)",
        "water hoses or connections at the back",
        "often a sleek, boxy shape",
        "front-loading or top-loading door",
        "round door (for front-loading machines)"
    ],
    "watch-101": [
        "A clasp or buckle to secure the strap/band",
        "A strap or band that may be made of leather, metal, plastic, or fabric",
        "Hour, minute, and possibly second hands",
        "Buttons around the face/dial for additional functions (common in digital or multifunction watches)",
        "A crown or dial on the side for adjusting time"
    ],
    "waterfall": [
        "Flowing water descending vertically or nearly vertically",
        "Movement blur of water captured in the photo",
        "Mist or spray near the base of the falling water",
        "A pool or basin of water at the bottom",
        "A continuous cascade or series of cascades"
    ],
    "watermelon": [
        "numerous black or white seeds embedded in the flesh (if cut open)",
        "vibrant red or pink flesh (if cut open)",
        "textured or smooth surface on the rind",
        "thick rind",
        "large, round or oval shape"
    ],
    "welding-mask": [
        "sometimes has side windows for peripheral vision",
        "protective headgear",
        "helmet-like structure covering the face",
        "adjustable headband or straps",
        "generally dark or metallic colors"
    ],
    "wheelbarrow": [
        "two handles extending from the back",
        "often used for carrying heavy loads",
        "a pair of supporting legs at the rear",
        "typically made of metal or plastic",
        "usually found in construction sites, gardens, or farms"
    ],
    "windmill": [
        "large, rotating blades or sails attached to a central hub",
        "horizontal or slightly inclined axis",
        "often cylindrical or conical base",
        "rural or open landscape setting",
        "sometimes a small building or housing at the base"
    ],
    "wine-bottle": [
        "dark green, brown, or clear color",
        "filled with liquid, usually visible through the glass",
        "typically made of glass",
        "cork, screw cap, or other closure at the top",
        "narrow neck"
    ],
    "xylophone": [
        "bars of varying lengths (longer bars produce lower pitches, shorter bars produce higher pitches)",
        "often a frame or stand supporting the bars",
        "bars arranged in a horizontal layout",
        "resonator tubes beneath the bars (in some models)",
        "a series of wooden or metal bars"
    ],
    "yarmulke": [
        "can be knit, cloth, or suede",
        "might be seen in religious or ceremonial contexts",
        "typically worn on the crown of the head",
        "may be worn by males, especially within Jewish communities",
        "fits snugly without straps or ties"
    ],
    "yo-yo": [
        "two round discs connected by an axle",
        "can be a variety of colors",
        "some models might have design patterns or logos on the discs",
        "usually made of plastic, wood, or metal",
        "may have a small knob or indentation in the center for gripping"
    ],
    "zebra": [
        "black and white striped coat",
        "mane running along the neck",
        "long tail with a tuft of hair at the end",
        "hooves",
        "large, pointed ears"
    ],
    "airplanes-101": [
        "cockpit windows",
        "a fuselage (the main body of the airplane)",
        "landing gear (wheels, skids, or floats)",
        "one or more engines (jet engines or propellers)",
        "passenger windows (if a commercial aircraft)"
    ],
    "car-side-101": [
        "Doors (typically two or four)",
        "Door handles",
        "Wheels and tires visible along the bottom",
        "Windows along the side",
        "Side mirrors protruding near the front windows"
    ],
    "faces-easy-101": [],
    "greyhound": [
        "deep chest",
        "thin face with a long muzzle",
        "long legs",
        "small, folded ears (often referred to as \"rose\" ears)",
        "sleek, slender body"
    ],
    "tennis-shoes": [
        "",
        "often multicolored, with brand logos",
        "reinforced toes and heels",
        "laces for fastening",
        "typically low-top or mid-top design"
    ],
    "toad": [
        "broad, flattened head",
        "squat, robust body",
        "warty, rough skin",
        "short legs relative to body size",
        "colors ranging from brown, gray, olive, or tan"
    ],
    "clutter": [
        "Presence of multiple, often unrelated objects",
        "Items overlapping or stacked irregularly",
        "Limited visible surface area (such as floors or tables) due to the abundance of items",
        "Lack of clear organization or arrangement",
        "Objects scattered haphazardly"
    ]
}